fw_storage/__init__.py
fw_storage/config.py
fw_storage/errors.py
fw_storage/fileinfo.py
fw_storage/filters.py
fw_storage/py.typed
fw_storage/storage.py
fw_storage/future/__init__.py
fw_storage/future/base.py
fw_storage/future/errors.py
fw_storage/future/utils.py
fw_storage/future/types/__init__.py
fw_storage/future/types/fs.py
fw_storage/types/__init__.py
fw_storage/types/az.py
fw_storage/types/fs.py
fw_storage/types/gs.py
fw_storage/types/s3.py
fw_storage-3.8.4.dist-info/METADATA
fw_storage-3.8.4.dist-info/WHEEL
fw_storage-3.8.4.dist-info/licenses/LICENSE
fw_storage-3.8.4.dist-info/RECORD
