Metadata-Version: 2.4
Name: fw-storage
Version: 3.8.4
Summary: Unified storage interface.
Project-URL: Repository, https://gitlab.com/flywheel-io/tools/lib/fw-storage
Project-URL: Documentation, https://gitlab.com/flywheel-io/tools/lib/fw-storage
Author-email: Flywheel <support@flywheel.io>
License-Expression: MIT
License-File: LICENSE
Keywords: Flywheel,file,object,storage
Classifier: Topic :: Software Development :: Libraries :: Python Modules
Requires-Python: >=3.11
Requires-Dist: azure-identity<2,>=1.11.0
Requires-Dist: azure-storage-blob>12.22.0
Requires-Dist: boto3<2,>=1.17.7
Requires-Dist: fw-utils>=4.2.2
Requires-Dist: google-cloud-storage<4,>=3.1.0
Requires-Dist: pydantic<3,>=2.3.0
Requires-Dist: typing-extensions<5,>=4.9.0
